LICENSE
MANIFEST.in
README.rst
setup.py
CrawlerCodePythonTools_WebBot.egg-info/PKG-INFO
CrawlerCodePythonTools_WebBot.egg-info/SOURCES.txt
CrawlerCodePythonTools_WebBot.egg-info/dependency_links.txt
CrawlerCodePythonTools_WebBot.egg-info/requires.txt
CrawlerCodePythonTools_WebBot.egg-info/top_level.txt
pythontools/webbot/__init__.py
pythontools/webbot/webbot.py