Metadata-Version: 2.1
Name: CrawlerCodePythonTools-WebBot
Version: 1.4.0
Summary: UNKNOWN
Home-page: https://github.com/CrawlerCode
Author: CrawlerCode
Author-email: 
License: UNKNOWN
Platform: UNKNOWN
